package/__init__.py
package/cons_var_term.py
package/main.py
package/minmax_term.py
package/solver.py
solve_sum_minmax-0.1.0.dist-info/LICENSE
solve_sum_minmax-0.1.0.dist-info/METADATA
solve_sum_minmax-0.1.0.dist-info/WHEEL
solve_sum_minmax-0.1.0.dist-info/top_level.txt
solve_sum_minmax-0.1.0.dist-info/RECORD
