Metadata-Version: 2.1
Name: solve-sum-minmax
Version: 0.1.0
Summary: A package to solve the sum of min/max equations
Home-page: https://github.com/hegelim/solve-sum-minmax
Author: Yewen Zhou
Author-email: yz4175@columbia.edu
License: UNKNOWN
Platform: UNKNOWN
Classifier: Programming Language :: Python :: 3
Classifier: License :: OSI Approved :: MIT License
Classifier: Operating System :: OS Independent
Requires-Python: >=3.6
License-File: LICENSE
